sentier_data_tools/__init__.py
sentier_data_tools/data_source_base.py
sentier_data_tools/licenses.py
sentier_data_tools/logs.py
sentier_data_tools/patch_pandas.py
sentier_data_tools/unit_conversion.py
sentier_data_tools/datapackage/__init__.py
sentier_data_tools/datapackage/datapackage.py
sentier_data_tools/datapackage/validation.py
sentier_data_tools/example/__init__.py
sentier_data_tools/example/data.py
sentier_data_tools/example/electrolyzers.xlsx
sentier_data_tools/example/model.py
sentier_data_tools/iri/__init__.py
sentier_data_tools/iri/main.py
sentier_data_tools/iri/utils.py
sentier_data_tools/local_storage/__init__.py
sentier_data_tools/local_storage/datasource.py
sentier_data_tools/local_storage/db.py
sentier_data_tools/local_storage/enum_field.py
sentier_data_tools/local_storage/fields.py
sentier_data_tools/model/__init__.py
sentier_data_tools/model/arguments.py
sentier_data_tools/model/base.py
sentier_data_tools-0.5.2.dist-info/LICENSE
sentier_data_tools-0.5.2.dist-info/METADATA
sentier_data_tools-0.5.2.dist-info/WHEEL
sentier_data_tools-0.5.2.dist-info/top_level.txt
sentier_data_tools-0.5.2.dist-info/RECORD
