Metadata-Version: 2.1
Name: sentier_data_tools
Version: 0.5.2
Summary: Basic tools to test and interact with Sentier.dev vocabulary and data systems
Author-email: Chris Mutel <cmutel@gmail.com>
Maintainer-email: Chris Mutel <cmutel@gmail.com>
Project-URL: source, https://github.com/sentier-dev/sentier_data_tools
Project-URL: homepage, https://github.com/sentier-dev/sentier_data_tools
Project-URL: tracker, https://github.com/sentier-dev/sentier_data_tools/issues
Classifier: Development Status :: 4 - Beta
Classifier: Programming Language :: Python
Classifier: Programming Language :: Python :: 3
Classifier: Programming Language :: Python :: 3.10
Classifier: Programming Language :: Python :: 3.11
Classifier: Programming Language :: Python :: 3.12
Classifier: Natural Language :: English
Classifier: Operating System :: OS Independent
Classifier: Topic :: Scientific/Engineering
Requires-Python: >=3.11
License-File: LICENSE
Requires-Dist: openpyxl
Requires-Dist: pandas
Requires-Dist: pandas-flavor
Requires-Dist: peewee
Requires-Dist: platformdirs
Requires-Dist: pyarrow
Requires-Dist: pydantic
Requires-Dist: rdflib
Requires-Dist: rfc3987
Requires-Dist: SPARQLWrapper
Requires-Dist: structlog
Provides-Extra: dev
Requires-Dist: build ; extra == 'dev'
Requires-Dist: pre-commit ; extra == 'dev'
Requires-Dist: pylint ; extra == 'dev'
Requires-Dist: pytest ; extra == 'dev'
Requires-Dist: pytest-cov ; extra == 'dev'
Requires-Dist: pytest-randomly ; extra == 'dev'
Requires-Dist: setuptools ; extra == 'dev'
Provides-Extra: testing
Requires-Dist: sentier-data-tools ; extra == 'testing'
Requires-Dist: pytest ; extra == 'testing'
Requires-Dist: pytest-cov ; extra == 'testing'
Requires-Dist: python-coveralls ; extra == 'testing'
